README.rst
setup.py
vrmapi/__init__.py
vrmapi/tests.py
vrmapi/utils.py
vrmapi/vrm.py
vrmapi.egg-info/PKG-INFO
vrmapi.egg-info/SOURCES.txt
vrmapi.egg-info/dependency_links.txt
vrmapi.egg-info/requires.txt
vrmapi.egg-info/top_level.txt