Metadata-Version: 1.0
Name: vrmapi
Version: 0.1.3
Summary: Victron python api
Home-page: UNKNOWN
Author: UNKNOWN
Author-email: UNKNOWN
License: UNKNOWN
Platform: UNKNOWN
